Metadata-Version: 2.1
Name: faciljsondb
Version: 0.0.5
Summary: Un paque te encargado de ayudarte a hacer base de datos censillas en json
Home-page: https://github.com/reymundus2/facil-json-db
Author: REYMUNDUS
Author-email: arceleandro2016@gmail.com
License: UNKNOWN
Platform: UNKNOWN
